magicdaq/__init__.py
magicdaq/api_class.py
magicdaq/client64.py
magicdaq/exceptions.py
magicdaq/load_library.py
magicdaq/loadlib.py
magicdaq/magicdaq.py
magicdaq/magicdaq_client_64bit.py
magicdaq/magicdaq_server_32bit.py
magicdaq/server32-windows.exe
magicdaq/server32-windows.exe.config
magicdaq/server32.py
magicdaq/utils.py
magicdaq-0.0.20.dist-info/LICENSE.txt
magicdaq-0.0.20.dist-info/METADATA
magicdaq-0.0.20.dist-info/WHEEL
magicdaq-0.0.20.dist-info/top_level.txt
magicdaq-0.0.20.dist-info/RECORD
