Metadata-Version: 2.1
Name: magicdaq
Version: 0.0.20
Summary: Python API for MagicDAQ Data Acquisition and Test Automation Device
Home-page: https://www.magicdaq.com/
Author: MagicDAQ Support
Author-email: support@magicdaq.com
License: UNKNOWN
Platform: UNKNOWN
Classifier: Programming Language :: Python :: 3
Classifier: License :: OSI Approved :: MIT License
Classifier: Operating System :: Microsoft :: Windows 
Requires-Python: >=3.0
